nanobot/__init__.py
nanobot/__main__.py
nanobot/agent/__init__.py
nanobot/agent/context.py
nanobot/agent/loop.py
nanobot/agent/memory.py
nanobot/agent/skills.py
nanobot/agent/tools/__init__.py
nanobot/agent/tools/base.py
nanobot/agent/tools/filesystem.py
nanobot/agent/tools/message.py
nanobot/agent/tools/registry.py
nanobot/agent/tools/shell.py
nanobot/agent/tools/web.py
nanobot/bus/__init__.py
nanobot/bus/events.py
nanobot/bus/queue.py
nanobot/channels/__init__.py
nanobot/channels/base.py
nanobot/channels/manager.py
nanobot/channels/telegram.py
nanobot/channels/whatsapp.py
nanobot/cli/__init__.py
nanobot/cli/commands.py
nanobot/config/__init__.py
nanobot/config/loader.py
nanobot/config/schema.py
nanobot/cron/__init__.py
nanobot/cron/service.py
nanobot/cron/types.py
nanobot/heartbeat/__init__.py
nanobot/heartbeat/service.py
nanobot/providers/__init__.py
nanobot/providers/base.py
nanobot/providers/litellm_provider.py
nanobot/session/__init__.py
nanobot/session/manager.py
nanobot/skills/github/SKILL.md
nanobot/skills/skill-creator/SKILL.md
nanobot/skills/summarize/SKILL.md
nanobot/skills/tmux/SKILL.md
nanobot/skills/tmux/scripts/find-sessions.sh
nanobot/skills/tmux/scripts/wait-for-text.sh
nanobot/skills/weather/SKILL.md
nanobot/utils/__init__.py
nanobot/utils/helpers.py
nanobot/bridge/package.json
nanobot/bridge/tsconfig.json
nanobot/bridge/src/index.ts
nanobot/bridge/src/server.ts
nanobot/bridge/src/types.d.ts
nanobot/bridge/src/whatsapp.ts
nanobot_ai-0.1.3.post1.dist-info/METADATA
nanobot_ai-0.1.3.post1.dist-info/WHEEL
nanobot_ai-0.1.3.post1.dist-info/entry_points.txt
nanobot_ai-0.1.3.post1.dist-info/licenses/LICENSE
nanobot_ai-0.1.3.post1.dist-info/RECORD
