Metadata-Version: 2.4
Name: nanobot-ai
Version: 0.1.3.post1
Summary: A lightweight personal AI assistant framework
Author: nanobot contributors
License: MIT
License-File: LICENSE
Keywords: agent,ai,chatbot
Classifier: Development Status :: 3 - Alpha
Classifier: Intended Audience :: Developers
Classifier: License :: OSI Approved :: MIT License
Classifier: Programming Language :: Python :: 3.11
Classifier: Programming Language :: Python :: 3.12
Requires-Python: >=3.11
Requires-Dist: croniter>=2.0.0
Requires-Dist: httpx>=0.25.0
Requires-Dist: litellm>=1.0.0
Requires-Dist: loguru>=0.7.0
Requires-Dist: pydantic-settings>=2.0.0
Requires-Dist: pydantic>=2.0.0
Requires-Dist: python-telegram-bot>=21.0
Requires-Dist: readability-lxml>=0.8.0
Requires-Dist: rich>=13.0.0
Requires-Dist: typer>=0.9.0
Requires-Dist: websocket-client>=1.6.0
Requires-Dist: websockets>=12.0
Provides-Extra: dev
Requires-Dist: pytest-asyncio>=0.21.0; extra == 'dev'
Requires-Dist: pytest>=7.0.0; extra == 'dev'
Requires-Dist: ruff>=0.1.0; extra == 'dev'
